{
  "pipelineSpec": {
    "components": {
      "comp-bigquery-create-model-job": {
        "executorLabel": "exec-bigquery-create-model-job",
        "inputDefinitions": {
          "parameters": {
            "job_configuration_query": {
              "type": "STRING"
            },
            "labels": {
              "type": "STRING"
            },
            "location": {
              "type": "STRING"
            },
            "project": {
              "type": "STRING"
            },
            "query": {
              "type": "STRING"
            },
            "query_parameters": {
              "type": "STRING"
            }
          }
        },
        "outputDefinitions": {
          "artifacts": {
            "model": {
              "artifactType": {
                "schemaTitle": "google.BQMLModel",
                "schemaVersion": "0.0.1"
              }
            }
          },
          "parameters": {
            "gcp_resources": {
              "type": "STRING"
            }
          }
        }
      },
      "comp-bigquery-evaluate-model-job": {
        "executorLabel": "exec-bigquery-evaluate-model-job",
        "inputDefinitions": {
          "artifacts": {
            "model": {
              "artifactType": {
                "schemaTitle": "google.BQMLModel",
                "schemaVersion": "0.0.1"
              }
            }
          },
          "parameters": {
            "job_configuration_query": {
              "type": "STRING"
            },
            "labels": {
              "type": "STRING"
            },
            "location": {
              "type": "STRING"
            },
            "project": {
              "type": "STRING"
            },
            "query_parameters": {
              "type": "STRING"
            },
            "query_statement": {
              "type": "STRING"
            },
            "table_name": {
              "type": "STRING"
            },
            "threshold": {
              "type": "DOUBLE"
            }
          }
        },
        "outputDefinitions": {
          "artifacts": {
            "evaluation_metrics": {
              "artifactType": {
                "schemaTitle": "system.Artifact",
                "schemaVersion": "0.0.1"
              }
            }
          },
          "parameters": {
            "gcp_resources": {
              "type": "STRING"
            }
          }
        }
      },
      "comp-bigquery-predict-model-job": {
        "executorLabel": "exec-bigquery-predict-model-job",
        "inputDefinitions": {
          "artifacts": {
            "model": {
              "artifactType": {
                "schemaTitle": "google.BQMLModel",
                "schemaVersion": "0.0.1"
              }
            }
          },
          "parameters": {
            "job_configuration_query": {
              "type": "STRING"
            },
            "labels": {
              "type": "STRING"
            },
            "location": {
              "type": "STRING"
            },
            "project": {
              "type": "STRING"
            },
            "query_parameters": {
              "type": "STRING"
            },
            "query_statement": {
              "type": "STRING"
            },
            "table_name": {
              "type": "STRING"
            },
            "threshold": {
              "type": "DOUBLE"
            }
          }
        },
        "outputDefinitions": {
          "artifacts": {
            "destination_table": {
              "artifactType": {
                "schemaTitle": "google.BQTable",
                "schemaVersion": "0.0.1"
              }
            }
          },
          "parameters": {
            "gcp_resources": {
              "type": "STRING"
            }
          }
        }
      },
      "comp-interpret-bqml-evaluation-metrics": {
        "executorLabel": "exec-interpret-bqml-evaluation-metrics",
        "inputDefinitions": {
          "artifacts": {
            "bqml_evaluation_metrics": {
              "artifactType": {
                "schemaTitle": "system.Artifact",
                "schemaVersion": "0.0.1"
              }
            }
          }
        },
        "outputDefinitions": {
          "artifacts": {
            "metrics": {
              "artifactType": {
                "schemaTitle": "system.Metrics",
                "schemaVersion": "0.0.1"
              }
            }
          }
        }
      }
    },
    "deploymentSpec": {
      "executors": {
        "exec-bigquery-create-model-job": {
          "container": {
            "args": [
              "--type",
              "BigqueryCreateModelJob",
              "--project",
              "{{$.inputs.parameters['project']}}",
              "--location",
              "{{$.inputs.parameters['location']}}",
              "--payload",
              "{\"configuration\": {\"query\": {{$.inputs.parameters['job_configuration_query']}}, \"labels\": {{$.inputs.parameters['labels']}}}}",
              "--job_configuration_query_override",
              "{\"query\": \"{{$.inputs.parameters['query']}}\", \"query_parameters\": {{$.inputs.parameters['query_parameters']}}}",
              "--gcp_resources",
              "{{$.outputs.parameters['gcp_resources'].output_file}}",
              "--executor_input",
              "{{$}}"
            ],
            "command": [
              "python3",
              "-u",
              "-m",
              "google_cloud_pipeline_components.container.v1.gcp_launcher.launcher"
            ],
            "image": "gcr.io/ml-pipeline/google-cloud-pipeline-components:1.0.11"
          }
        },
        "exec-bigquery-evaluate-model-job": {
          "container": {
            "args": [
              "--type",
              "BigqueryEvaluateModelJob",
              "--project",
              "{{$.inputs.parameters['project']}}",
              "--location",
              "{{$.inputs.parameters['location']}}",
              "--model_name",
              "{{$.inputs.artifacts['model'].metadata['projectId']}}.{{$.inputs.artifacts['model'].metadata['datasetId']}}.{{$.inputs.artifacts['model'].metadata['modelId']}}",
              "--table_name",
              "{{$.inputs.parameters['table_name']}}",
              "--query_statement",
              "{{$.inputs.parameters['query_statement']}}",
              "--threshold",
              "{{$.inputs.parameters['threshold']}}",
              "--payload",
              "{\"configuration\": {\"query\": {{$.inputs.parameters['job_configuration_query']}}, \"labels\": {{$.inputs.parameters['labels']}}}}",
              "--job_configuration_query_override",
              "{\"query_parameters\": {{$.inputs.parameters['query_parameters']}}, \"destination_encryption_configuration\": {\"kmsKeyName\": \"\"}}",
              "--gcp_resources",
              "{{$.outputs.parameters['gcp_resources'].output_file}}",
              "--executor_input",
              "{{$}}"
            ],
            "command": [
              "python3",
              "-u",
              "-m",
              "google_cloud_pipeline_components.container.v1.gcp_launcher.launcher"
            ],
            "image": "gcr.io/ml-pipeline/google-cloud-pipeline-components:1.0.11"
          }
        },
        "exec-bigquery-predict-model-job": {
          "container": {
            "args": [
              "--type",
              "BigqueryPredictModelJob",
              "--project",
              "{{$.inputs.parameters['project']}}",
              "--location",
              "{{$.inputs.parameters['location']}}",
              "--model_name",
              "{{$.inputs.artifacts['model'].metadata['projectId']}}.{{$.inputs.artifacts['model'].metadata['datasetId']}}.{{$.inputs.artifacts['model'].metadata['modelId']}}",
              "--table_name",
              "{{$.inputs.parameters['table_name']}}",
              "--query_statement",
              "{{$.inputs.parameters['query_statement']}}",
              "--threshold",
              "{{$.inputs.parameters['threshold']}}",
              "--payload",
              "{\"configuration\": {\"query\": {{$.inputs.parameters['job_configuration_query']}}, \"labels\": {{$.inputs.parameters['labels']}}}}",
              "--job_configuration_query_override",
              "{\"query_parameters\": {{$.inputs.parameters['query_parameters']}}, \"destination_encryption_configuration\": {\"kmsKeyName\": \"\"}}",
              "--gcp_resources",
              "{{$.outputs.parameters['gcp_resources'].output_file}}",
              "--executor_input",
              "{{$}}"
            ],
            "command": [
              "python3",
              "-u",
              "-m",
              "google_cloud_pipeline_components.container.v1.gcp_launcher.launcher"
            ],
            "image": "gcr.io/ml-pipeline/google-cloud-pipeline-components:1.0.11"
          }
        },
        "exec-interpret-bqml-evaluation-metrics": {
          "container": {
            "args": [
              "--executor_input",
              "{{$}}",
              "--function_to_execute",
              "interpret_bqml_evaluation_metrics"
            ],
            "command": [
              "sh",
              "-c",
              "\nif ! [ -x \"$(command -v pip)\" ]; then\n    python3 -m ensurepip || python3 -m ensurepip --user || apt-get install python3-pip\nfi\n\nPIP_DISABLE_PIP_VERSION_CHECK=1 python3 -m pip install --quiet     --no-warn-script-location 'kfp==1.8.12' && \"$0\" \"$@\"\n",
              "sh",
              "-ec",
              "program_path=$(mktemp -d)\nprintf \"%s\" \"$0\" > \"$program_path/ephemeral_component.py\"\npython3 -m kfp.v2.components.executor_main                         --component_module_path                         \"$program_path/ephemeral_component.py\"                         \"$@\"\n",
              "\nimport kfp\nfrom kfp.v2 import dsl\nfrom kfp.v2.dsl import *\nfrom typing import *\n\ndef interpret_bqml_evaluation_metrics(\n    bqml_evaluation_metrics: Input[Artifact], metrics: Output[Metrics]\n):\n    import math\n\n    metadata = bqml_evaluation_metrics.metadata\n    for r in metadata[\"rows\"]:\n\n        rows = r[\"f\"]\n        schema = metadata[\"schema\"][\"fields\"]\n\n        output = {}\n        for metric, value in zip(schema, rows):\n            metric_name = metric[\"name\"]\n            val = float(value[\"v\"])\n            output[metric_name] = val\n            metrics.log_metric(metric_name, val)\n            if metric_name == \"mean_squared_error\":\n                rmse = math.sqrt(val)\n                metrics.log_metric(\"root_mean_squared_error\", rmse)\n\n    metrics.log_metric(\"framework\", \"BQML\")\n\n    print(output)\n\n"
            ],
            "image": "python:3.9"
          }
        }
      }
    },
    "pipelineInfo": {
      "name": "tabular-classification-bqml-pipeline"
    },
    "root": {
      "dag": {
        "outputs": {
          "artifacts": {
            "interpret-bqml-evaluation-metrics-metrics": {
              "artifactSelectors": [
                {
                  "outputArtifactKey": "metrics",
                  "producerSubtask": "interpret-bqml-evaluation-metrics"
                }
              ]
            }
          }
        },
        "tasks": {
          "bigquery-create-model-job": {
            "cachingOptions": {
              "enableCache": true
            },
            "componentRef": {
              "name": "comp-bigquery-create-model-job"
            },
            "inputs": {
              "parameters": {
                "job_configuration_query": {
                  "runtimeValue": {
                    "constantValue": {
                      "stringValue": "{}"
                    }
                  }
                },
                "labels": {
                  "runtimeValue": {
                    "constantValue": {
                      "stringValue": "{}"
                    }
                  }
                },
                "location": {
                  "componentInputParameter": "bq_location"
                },
                "pipelineparam--bq_table": {
                  "componentInputParameter": "bq_table"
                },
                "pipelineparam--label": {
                  "componentInputParameter": "label"
                },
                "pipelineparam--model": {
                  "componentInputParameter": "model"
                },
                "project": {
                  "componentInputParameter": "project"
                },
                "query": {
                  "runtimeValue": {
                    "constantValue": {
                      "stringValue": "CREATE OR REPLACE MODEL {{$.inputs.parameters['pipelineparam--model']}} OPTIONS (model_type='BOOSTED_TREE_REGRESSOR', labels=['{{$.inputs.parameters['pipelineparam--label']}}']) AS SELECT * FROM `{{$.inputs.parameters['pipelineparam--bq_table']}}`"
                    }
                  }
                },
                "query_parameters": {
                  "runtimeValue": {
                    "constantValue": {
                      "stringValue": "[]"
                    }
                  }
                }
              }
            },
            "taskInfo": {
              "name": "bigquery-create-model-job"
            }
          },
          "bigquery-evaluate-model-job": {
            "cachingOptions": {
              "enableCache": true
            },
            "componentRef": {
              "name": "comp-bigquery-evaluate-model-job"
            },
            "dependentTasks": [
              "bigquery-create-model-job"
            ],
            "inputs": {
              "artifacts": {
                "model": {
                  "taskOutputArtifact": {
                    "outputArtifactKey": "model",
                    "producerTask": "bigquery-create-model-job"
                  }
                }
              },
              "parameters": {
                "job_configuration_query": {
                  "runtimeValue": {
                    "constantValue": {
                      "stringValue": "{}"
                    }
                  }
                },
                "labels": {
                  "runtimeValue": {
                    "constantValue": {
                      "stringValue": "[]"
                    }
                  }
                },
                "location": {
                  "componentInputParameter": "bq_location"
                },
                "project": {
                  "componentInputParameter": "project"
                },
                "query_parameters": {
                  "runtimeValue": {
                    "constantValue": {
                      "stringValue": "[]"
                    }
                  }
                },
                "query_statement": {
                  "runtimeValue": {
                    "constantValue": {
                      "stringValue": ""
                    }
                  }
                },
                "table_name": {
                  "runtimeValue": {
                    "constantValue": {
                      "stringValue": ""
                    }
                  }
                },
                "threshold": {
                  "runtimeValue": {
                    "constantValue": {
                      "doubleValue": -1.0
                    }
                  }
                }
              }
            },
            "taskInfo": {
              "name": "bigquery-evaluate-model-job"
            }
          },
          "bigquery-predict-model-job": {
            "cachingOptions": {
              "enableCache": true
            },
            "componentRef": {
              "name": "comp-bigquery-predict-model-job"
            },
            "dependentTasks": [
              "bigquery-create-model-job"
            ],
            "inputs": {
              "artifacts": {
                "model": {
                  "taskOutputArtifact": {
                    "outputArtifactKey": "model",
                    "producerTask": "bigquery-create-model-job"
                  }
                }
              },
              "parameters": {
                "job_configuration_query": {
                  "runtimeValue": {
                    "constantValue": {
                      "stringValue": "{\"destinationTable\": {\"projectId\": \"svc-demo-vertex\", \"datasetId\": \"pipeline_us\", \"tableId\": \"results_abalone\"}, \"createDisposition\": \"CREATE_IF_NEEDED\", \"writeDisposition\": \"WRITE_TRUNCATE\"}"
                    }
                  }
                },
                "labels": {
                  "runtimeValue": {
                    "constantValue": {
                      "stringValue": "{}"
                    }
                  }
                },
                "location": {
                  "componentInputParameter": "bq_location"
                },
                "pipelineparam--bq_table": {
                  "componentInputParameter": "bq_table"
                },
                "project": {
                  "componentInputParameter": "project"
                },
                "query_parameters": {
                  "runtimeValue": {
                    "constantValue": {
                      "stringValue": "[]"
                    }
                  }
                },
                "query_statement": {
                  "runtimeValue": {
                    "constantValue": {
                      "stringValue": ""
                    }
                  }
                },
                "table_name": {
                  "runtimeValue": {
                    "constantValue": {
                      "stringValue": "`{{$.inputs.parameters['pipelineparam--bq_table']}}`"
                    }
                  }
                },
                "threshold": {
                  "runtimeValue": {
                    "constantValue": {
                      "doubleValue": -1.0
                    }
                  }
                }
              }
            },
            "taskInfo": {
              "name": "bigquery-predict-model-job"
            }
          },
          "interpret-bqml-evaluation-metrics": {
            "cachingOptions": {
              "enableCache": true
            },
            "componentRef": {
              "name": "comp-interpret-bqml-evaluation-metrics"
            },
            "dependentTasks": [
              "bigquery-evaluate-model-job"
            ],
            "inputs": {
              "artifacts": {
                "bqml_evaluation_metrics": {
                  "taskOutputArtifact": {
                    "outputArtifactKey": "evaluation_metrics",
                    "producerTask": "bigquery-evaluate-model-job"
                  }
                }
              }
            },
            "taskInfo": {
              "name": "interpret-bqml-evaluation-metrics"
            }
          }
        }
      },
      "inputDefinitions": {
        "parameters": {
          "bq_location": {
            "type": "STRING"
          },
          "bq_table": {
            "type": "STRING"
          },
          "label": {
            "type": "STRING"
          },
          "model": {
            "type": "STRING"
          },
          "project": {
            "type": "STRING"
          },
          "region": {
            "type": "STRING"
          }
        }
      },
      "outputDefinitions": {
        "artifacts": {
          "interpret-bqml-evaluation-metrics-metrics": {
            "artifactType": {
              "schemaTitle": "system.Metrics",
              "schemaVersion": "0.0.1"
            }
          }
        }
      }
    },
    "schemaVersion": "2.0.0",
    "sdkVersion": "kfp-1.8.12"
  },
  "runtimeConfig": {}
}